tquiet.py
tquiet-0.1.0.dist-info/WHEEL
tquiet-0.1.0.dist-info/METADATA
tquiet-0.1.0.dist-info/RECORD
