Metadata-Version: 2.3
Name: tquiet
Version: 0.1.0
Summary: Mimic the `tqdm` progress bar interface, but don't actually display anything.
Author-email: Kale Kundert <kale@thekunderts.net>
Requires-Python: ~=3.10
Classifier: Programming Language :: Python :: 3
Requires-Dist: sphinx ; extra == "doc"
Requires-Dist: sphinx_rtd_theme ; extra == "doc"
Requires-Dist: myst_parser ; extra == "doc"
Requires-Dist: autoclasstoc ; extra == "doc"
Requires-Dist: pytest ; extra == "test"
Requires-Dist: parametrize_from_file ; extra == "test"
Project-URL: Bug Tracker, https://github.com/kalekundert/tquiet/issues
Project-URL: Continuous Integration, https://github.com/kalekundert/tquiet/actions
Project-URL: Documentation, https://tquiet.readthedocs.io/en/latest/
Project-URL: Test Coverage, https://app.codecov.io/github/kalekundert/tquiet
Project-URL: Version Control, https://github.com/kalekundert/tquiet
Provides-Extra: doc
Provides-Extra: test
